virtmat/__init__.py
virtmat/middleware/__init__.py
virtmat/middleware/exceptions.py
virtmat/middleware/utilities.py
virtmat/middleware/cli/__init__.py
virtmat/middleware/cli/run_resconfig.py
virtmat/middleware/cli/run_wfengine.py
virtmat/middleware/engine/__init__.py
virtmat/middleware/engine/wfengine.json
virtmat/middleware/engine/wfengine.py
virtmat/middleware/engine/wfengine_jupyter.py
virtmat/middleware/engine/wfengine_remote.py
virtmat/middleware/query/__init__.py
virtmat/middleware/query/dbquery.py
virtmat/middleware/query/wfquery.py
virtmat/middleware/resconfig/__init__.py
virtmat/middleware/resconfig/cli.py
virtmat/middleware/resconfig/qadapter.py
virtmat/middleware/resconfig/resconfig.json
virtmat/middleware/resconfig/resconfig.py
vre_middleware-1.3.1.dist-info/licenses/LICENSE
vre_middleware-1.3.1.dist-info/METADATA
vre_middleware-1.3.1.dist-info/WHEEL
vre_middleware-1.3.1.dist-info/entry_points.txt
vre_middleware-1.3.1.dist-info/top_level.txt
vre_middleware-1.3.1.dist-info/RECORD
